getjump/__init__.py
getjump/getjump.py
getjump/main.py
getjump/py.typed
getjump-2.10.0.dist-info/METADATA
getjump-2.10.0.dist-info/WHEEL
getjump-2.10.0.dist-info/entry_points.txt
getjump-2.10.0.dist-info/licenses/LICENSE.txt
getjump-2.10.0.dist-info/RECORD
