Metadata-Version: 2.4
Name: getjump
Version: 2.10.0
Summary: Get and save images from jump web viewer
Project-URL: Repository, https://github.com/eggplants/getjump
Author-email: eggplants <w10776e8w@yahoo.co.jp>
License: MIT
License-File: LICENSE.txt
Keywords: cli,downloader,manga
Classifier: License :: OSI Approved :: MIT License
Classifier: Programming Language :: Python :: 3 :: Only
Classifier: Programming Language :: Python :: 3.10
Classifier: Programming Language :: Python :: 3.11
Classifier: Programming Language :: Python :: 3.12
Classifier: Programming Language :: Python :: 3.13
Classifier: Programming Language :: Python :: 3.14
Classifier: Topic :: Text Processing :: Linguistic
Classifier: Typing :: Typed
Requires-Python: <4,>=3.10
Requires-Dist: beautifulsoup4<5,>=4.12.3
Requires-Dist: pillow<13,>=11.1
Requires-Dist: requests<3,>=2.32.3
Requires-Dist: rich<15,>=13.9.4
